<?xml version="1.0" encoding="UTF-8"?>
<!DOCTYPE suite SYSTEM "http://testng.org/testng-1.0.dtd">
<suite thread-count="3" name="Suite" parallel="tests">

	<test name="ChromeTest">
		<parameter name="Browser" value="Chrome" />
		<classes>
			<class name="GridConcepts.SeleniumGridsTests" />
		</classes>
	</test>

	<test name="FirefoxTest">
		<parameter name="Browser" value="Firefox" />
		<classes>
			<class name="GridConcepts.SeleniumGridsTests" />
		</classes>
	</test>

	<test name="IETest">
		<parameter name="Browser" value="IE" />
		<classes>
			<class name="GridConcepts.SeleniumGridsTests" />
		</classes>
	</test>

</suite>
